{
  "users": [
    {
      "id": "4b0900d9-b755-499b-9644-b84827d32092",
      "username": "a",
      "password": "a",
      "email": "a@a.com",
      "profile": {
        "followers": 5,
        "flakes": 8238,
        "country": "N/A",
        "hobby": "N/A",
        "emoji": "❄️",
        "userSince": "2024-03-28"
      }
    },
    {
      "id": "233a3563-ed31-4518-aa4e-475312575b11",
      "username": "1",
      "password": "1",
      "email": "test@test.com",
      "profile": {
        "followers": 0,
        "flakes": 0,
        "country": "N/A",
        "hobby": "N/A",
        "emoji": "❄️",
        "userSince": "2024-03-28"
      }
    }
  ],
  "posts": [
    {
      "id": "2d34ad72-5",
      "profileImage": "/images/default-user-image.png",
      "body": "qhggsfchjagcagscjhackahsc",
      "date": "3-29",
      "userID": "4b0900d9-b755-499b-9644-b84827d32092",
      "flakes": 2
    },
    {
      "id": "27422568-d",
      "profileImage": "/images/default-user-image.png",
      "body": "sdvsadvsadv",
      "date": "3-29",
      "userID": "4b0900d9-b755-499b-9644-b84827d32092",
      "flakes": 1
    },
    {
      "id": "67e494fc-b",
      "profileImage": "/images/default-user-image.png",
      "body": "dsvdsvsdfvsdvf",
      "date": "3-29",
      "userID": "4b0900d9-b755-499b-9644-b84827d32092",
      "flakes": 1
    }
  ]
}